.gitignore
.travis.yml
CHANGES.rst
MANIFEST.in
README.rst
bootstrap.py
buildout.cfg
collective.cmcicpaiement-configure.zcml
setup.py
travis.cfg
collective/__init__.py
collective.cmcicpaiement.egg-info/PKG-INFO
collective.cmcicpaiement.egg-info/SOURCES.txt
collective.cmcicpaiement.egg-info/dependency_links.txt
collective.cmcicpaiement.egg-info/entry_points.txt
collective.cmcicpaiement.egg-info/namespace_packages.txt
collective.cmcicpaiement.egg-info/not-zip-safe
collective.cmcicpaiement.egg-info/requires.txt
collective.cmcicpaiement.egg-info/top_level.txt
collective/cmcicpaiement/__init__.py
collective/cmcicpaiement/aller.py
collective/cmcicpaiement/aller_form.pt
collective/cmcicpaiement/configure.zcml
collective/cmcicpaiement/i18n.py
collective/cmcicpaiement/layer.py
collective/cmcicpaiement/rebuild_i18n.sh
collective/cmcicpaiement/retour.py
collective/cmcicpaiement/sceau.py
collective/cmcicpaiement/settings.py
collective/cmcicpaiement/testing.py
collective/cmcicpaiement/upgrades.py
collective/cmcicpaiement/upgrades.zcml
collective/cmcicpaiement/locales/collective.cmcicpaiement.pot
collective/cmcicpaiement/locales/en/LC_MESSAGES/collective.cmcicpaiement.po
collective/cmcicpaiement/locales/fr/LC_MESSAGES/collective.cmcicpaiement.po
collective/cmcicpaiement/profiles/default/browserlayer.xml
collective/cmcicpaiement/profiles/default/metadata.xml
collective/cmcicpaiement/profiles/default/registry.xml
collective/cmcicpaiement/tests/__init__.py
collective/cmcicpaiement/tests/base.py
collective/cmcicpaiement/tests/test_aller.py
collective/cmcicpaiement/tests/test_retour.py
collective/cmcicpaiement/tests/test_sceau.py
collective/cmcicpaiement/tests/test_setup.py
collective/cmcicpaiement/tests/utils.py