Metadata-Version: 1.0
Name: collective.cmcicpaiement
Version: 1.0b1
Summary: CM CIC Paiement for Plone
Home-page: http://svn.plone.org/svn/collective/
Author: UNKNOWN
Author-email: UNKNOWN
License: GPL
Keywords: Plone cmcicpaiement ecommerce
Platform: UNKNOWN
Classifier: Programming Language :: Python
Classifier: Framework :: Plone
Classifier: Framework :: Plone :: 4.0
Classifier: Framework :: Plone :: 4.1
Classifier: Framework :: Plone :: 4.2
